MANIFEST.in
README.md
setup.py
ginger_sdk/__init__.py
ginger_sdk/api_client.py
ginger_sdk/ginger.py
ginger_sdk/http_client.py
ginger_sdk.egg-info/PKG-INFO
ginger_sdk.egg-info/SOURCES.txt
ginger_sdk.egg-info/dependency_links.txt
ginger_sdk.egg-info/requires.txt
ginger_sdk.egg-info/top_level.txt