Metadata-Version: 2.1
Name: ginger-sdk
Version: 2.1.3
Summary: The official Ginger Payments Python SDK
Home-page: https://github.com/gingerpayments/ginger-python
Author: Ginger Payments
Author-email: dev@gingerpayments.com
License: UNKNOWN
Platform: UNKNOWN
Classifier: Programming Language :: Python :: 3
Classifier: Programming Language :: Python :: 3.6
Classifier: Programming Language :: Python :: 3.7
Classifier: License :: OSI Approved :: MIT License
Classifier: Operating System :: OS Independent
Classifier: Environment :: Web Environment
Classifier: Intended Audience :: Developers
Classifier: Topic :: Software Development :: Libraries :: Python Modules
Requires-Python: >=3.6
